codeanim/__init__.py
codeanim/chrome.py
codeanim/core.py
codeanim/delayer.py
codeanim/interpolators.py
codeanim/keyboard.py
codeanim/parser.py
codeanim/py.typed
codeanim/recorder.py
codeanim/shell.py
codeanim/vscode.py
codeanim-0.3.3.dist-info/WHEEL
codeanim-0.3.3.dist-info/entry_points.txt
codeanim-0.3.3.dist-info/METADATA
codeanim-0.3.3.dist-info/RECORD
