Metadata-Version: 2.3
Name: codeanim
Version: 0.3.3
Summary: A tool that automates presentation of software demos.
Author: Shad Sharma
Author-email: Shad Sharma <shadanan@gmail.com>
Requires-Dist: pynput>=1.8.1
Requires-Dist: pyperclip>=1.11.0
Requires-Python: >=3.13
